bitbar/__init__.py
bitbar/helper.py
bitbar_helper-0.2.0.dist-info/METADATA
bitbar_helper-0.2.0.dist-info/WHEEL
bitbar_helper-0.2.0.dist-info/entry_points.txt
bitbar_helper-0.2.0.dist-info/top_level.txt
bitbar_helper-0.2.0.dist-info/RECORD
