Metadata-Version: 2.1
Name: bitbar_helper
Version: 0.2.0
Summary: bitbar python pkg
Author: Paul Traylor
Classifier: Operating System :: OS Independent
Classifier: Programming Language :: Python :: 3 :: Only
Classifier: Programming Language :: Python :: 3
Classifier: Programming Language :: Python :: 3.10
Classifier: Programming Language :: Python :: 3.6
Classifier: Programming Language :: Python :: 3.7
Classifier: Programming Language :: Python :: 3.8
Classifier: Programming Language :: Python :: 3.9
Requires-Python: >=3.6
Requires-Dist: importlib-metadata >=1.0 ; python_version < "3.8"
